worldcluster/__init__.py
worldcluster/cli.py
worldcluster/worldcluster.py
worldcluster-1.1.0.dist-info/METADATA
worldcluster-1.1.0.dist-info/WHEEL
worldcluster-1.1.0.dist-info/entry_points.txt
worldcluster-1.1.0.dist-info/top_level.txt
worldcluster-1.1.0.dist-info/RECORD
