Metadata-Version: 2.4
Name: worldcluster
Version: 1.1.0
Summary: A lightweight distributed parallel processing cluster for LAN/Tailscale/ZeroTier networks.
Author: Your Name
Requires-Python: >=3.8
Dynamic: author
Dynamic: requires-python
Dynamic: summary
